{
    "props": {
        "pageProps": {
            "colorScheme": "dark",
            "cookies": {
                "referrals": {}
            },
            "canIndex": true,
            "session": null,
            "settings": {
                "newsletterSubscriber": true
            },
            "flags": {
                "earlyAccessModel": true,
                "apiKeys": true,
                "ambientCard": true,
                "gallery": true,
                "posts": false,
                "articles": true,
                "articleCreate": true,
                "adminTags": false,
                "civitaiLink": false,
                "stripe": false,
                "imageTraining": false,
                "videoTraining": false,
                "imageTrainingResults": false,
                "sdxlGeneration": true,
                "questions": false,
                "imageGeneration": true,
                "largerGenerationImages": true,
                "enhancedSearch": true,
                "alternateHome": true,
                "collections": true,
                "air": false,
                "profileCollections": true,
                "imageSearch": true,
                "buzz": true,
                "recommenders": false,
                "assistant": false,
                "assistantPersonality": false,
                "bounties": true,
                "newsroom": true,
                "safety": true,
                "csamReports": false,
                "appealReports": false,
                "reviewTrainingData": false,
                "clubs": false,
                "createClubs": false,
                "moderateTags": false,
                "chat": false,
                "creatorsProgram": false,
                "buzzWithdrawalTransfer": false,
                "vault": false,
                "draftMode": true,
                "membershipsV2": true,
                "cosmeticShop": true,
                "impersonation": false,
                "donationGoals": true,
                "creatorComp": true,
                "experimentalGen": false,
                "imageIndex": true,
                "imageIndexFeed": true,
                "isGreen": false,
                "isBlue": true,
                "isRed": false,
                "canViewNsfw": true,
                "canBuyBuzz": false,
                "customPaymentProvider": true,
                "adsEnabled": true,
                "paddleAdjustments": false,
                "announcements": false,
                "blocklists": false,
                "toolSearch": true,
                "generationOnlyModels": false,
                "appTour": true,
                "privateModels": false,
                "auctions": true
            },
            "seed": 1744862417140,
            "hasAuthCookie": false,
            "id": 654541,
            "trpcState": {
                "json": {
                    "mutations": [],
                    "queries": [
                        {
                            "state": {
                                "data": {
                                    "hiddenImages": [],
                                    "hiddenModels": [],
                                    "hiddenUsers": [],
                                    "hiddenTags": [
                                        {
                                            "id": 112944,
                                            "name": "sexual situations",
                                            "nsfwLevel": 4
                                        },
                                        {
                                            "id": 113675,
                                            "name": "physical violence",
                                            "nsfwLevel": 2
                                        },
                                        {
                                            "id": 126846,
                                            "name": "disturbing",
                                            "nsfwLevel": 4
                                        },
                                        {
                                            "id": 127175,
                                            "name": "male nudity",
                                            "nsfwLevel": 4
                                        },
                                        {
                                            "id": 113474,
                                            "name": "hanging",
                                            "nsfwLevel": 32
                                        },
                                        {
                                            "id": 113645,
                                            "name": "hate symbols",
                                            "nsfwLevel": 32
                                        },
                                        {
                                            "id": 113644,
                                            "name": "nazi party",
                                            "nsfwLevel": 32
                                        },
                                        {
                                            "id": 6924,
                                            "name": "revealing clothes",
                                            "nsfwLevel": 2
                                        },
                                        {
                                            "id": 112675,
                                            "name": "weapon violence",
                                            "nsfwLevel": 2
                                        },
                                        {
                                            "id": 112070,
                                            "name": "female swimwear or underwear",
                                            "nsfwLevel": 4
                                        },
                                        {
                                            "id": 111969,
                                            "name": "male swimwear or underwear",
                                            "nsfwLevel": 4
                                        },
                                        {
                                            "id": 111942,
                                            "name": "partial nudity",
                                            "nsfwLevel": 4
                                        },
                                        {
                                            "id": 113975,
                                            "name": "white supremacy",
                                            "nsfwLevel": 32
                                        },
                                        {
                                            "id": 113360,
                                            "name": "adult toys",
                                            "nsfwLevel": 8
                                        },
                                        {
                                            "id": 112481,
                                            "name": "graphic male nudity",
                                            "nsfwLevel": 8
                                        },
                                        {
                                            "id": 111851,
                                            "name": "illustrated explicit nudity",
                                            "nsfwLevel": 8
                                        },
                                        {
                                            "id": 2013,
                                            "name": "nudity",
                                            "nsfwLevel": 8
                                        },
                                        {
                                            "id": 111901,
                                            "name": "graphic violence or gore",
                                            "nsfwLevel": 4
                                        },
                                        {
                                            "id": 112683,
                                            "name": "graphic female nudity",
                                            "nsfwLevel": 8
                                        },
                                        {
                                            "id": 113487,
                                            "name": "corpses",
                                            "nsfwLevel": 2
                                        },
                                        {
                                            "id": 2635,
                                            "name": "wide hips",
                                            "nsfwLevel": 2
                                        },
                                        {
                                            "id": 163890,
                                            "name": "convenient censoring",
                                            "nsfwLevel": 2
                                        },
                                        {
                                            "id": 496,
                                            "name": "peeing",
                                            "nsfwLevel": 16
                                        },
                                        {
                                            "id": 145241,
                                            "name": "oral invitation",
                                            "nsfwLevel": 2
                                        },
                                        {
                                            "id": 112783,
                                            "name": "emaciated bodies",
                                            "nsfwLevel": 4
                                        },
                                        {
                                            "id": 224754,
                                            "name": "exposed female nipple",
                                            "nsfwLevel": 4
                                        },
                                        {
                                            "id": 5183,
                                            "name": "blowjob",
                                            "nsfwLevel": 16
                                        },
                                        {
                                            "id": 124097,
                                            "name": "female nudity",
                                            "nsfwLevel": 4
                                        },
                                        {
                                            "id": 111991,
                                            "name": "sexual activity",
                                            "nsfwLevel": 16
                                        },
                                        {
                                            "id": 306426,
                                            "name": "sexual intent",
                                            "nsfwLevel": 8
                                        },
                                        {
                                            "id": 168660,
                                            "name": "undressed",
                                            "nsfwLevel": 4
                                        },
                                        {
                                            "id": 162145,
                                            "name": "male underwear",
                                            "nsfwLevel": 4
                                        },
                                        {
                                            "id": 167855,
                                            "name": "female swimwear",
                                            "nsfwLevel": 4
                                        },
                                        {
                                            "id": 156190,
                                            "name": "genitals",
                                            "nsfwLevel": 8
                                        },
                                        {
                                            "id": 125026,
                                            "name": "female underwear",
                                            "nsfwLevel": 4
                                        },
                                        {
                                            "id": 2634,
                                            "name": "thick thighs",
                                            "nsfwLevel": 2
                                        },
                                        {
                                            "id": 162156,
                                            "name": "breasts out",
                                            "nsfwLevel": 4
                                        },
                                        {
                                            "id": 162751,
                                            "name": "strapless leotard",
                                            "nsfwLevel": 4
                                        },
                                        {
                                            "id": 2561,
                                            "name": "vore",
                                            "nsfwLevel": 16
                                        },
                                        {
                                            "id": 143969,
                                            "name": "breast out",
                                            "nsfwLevel": 4
                                        },
                                        {
                                            "id": 5686,
                                            "name": "one breast out",
                                            "nsfwLevel": 4
                                        },
                                        {
                                            "id": 5219,
                                            "name": "huge breasts",
                                            "nsfwLevel": 2
                                        },
                                        {
                                            "id": 5510,
                                            "name": "gigantic breasts",
                                            "nsfwLevel": 4
                                        },
                                        {
                                            "id": 173393,
                                            "name": "huge butt",
                                            "nsfwLevel": 4
                                        },
                                        {
                                            "id": 7088,
                                            "name": "covered nipples",
                                            "nsfwLevel": 4
                                        },
                                        {
                                            "id": 163133,
                                            "name": "hair over breasts",
                                            "nsfwLevel": 4
                                        },
                                        {
                                            "id": 116858,
                                            "name": "no panties",
                                            "nsfwLevel": 4
                                        },
                                        {
                                            "id": 164076,
                                            "name": "sitting on face",
                                            "nsfwLevel": 4
                                        },
                                        {
                                            "id": 2086,
                                            "name": "anal",
                                            "nsfwLevel": 16
                                        },
                                        {
                                            "id": 5146,
                                            "name": "sex",
                                            "nsfwLevel": 16
                                        },
                                        {
                                            "id": 137673,
                                            "name": "dildo riding",
                                            "nsfwLevel": 16
                                        },
                                        {
                                            "id": 117333,
                                            "name": "downblouse",
                                            "nsfwLevel": 2
                                        },
                                        {
                                            "id": 231,
                                            "name": "oral",
                                            "nsfwLevel": 16
                                        },
                                        {
                                            "id": 5195,
                                            "name": "cum",
                                            "nsfwLevel": 16
                                        },
                                        {
                                            "id": 243,
                                            "name": "porn",
                                            "nsfwLevel": 8
                                        },
                                        {
                                            "id": 279,
                                            "name": "futanari",
                                            "nsfwLevel": 8
                                        },
                                        {
                                            "id": 5218,
                                            "name": "hentai",
                                            "nsfwLevel": 8
                                        },
                                        {
                                            "id": 304,
                                            "name": "nude",
                                            "nsfwLevel": 4
                                        },
                                        {
                                            "id": 1718,
                                            "name": "lingerie",
                                            "nsfwLevel": 4
                                        },
                                        {
                                            "id": 190,
                                            "name": "sexy",
                                            "nsfwLevel": 2
                                        },
                                        {
                                            "id": 113935,
                                            "name": "nsfw",
                                            "nsfwLevel": 4
                                        },
                                        {
                                            "id": 111755,
                                            "name": "suggestive",
                                            "nsfwLevel": 2
                                        },
                                        {
                                            "id": 164048,
                                            "name": "child on child",
                                            "nsfwLevel": 32
                                        },
                                        {
                                            "id": 119736,
                                            "name": "bestiality",
                                            "nsfwLevel": 32
                                        },
                                        {
                                            "id": 164020,
                                            "name": "incest",
                                            "nsfwLevel": 32
                                        },
                                        {
                                            "id": 113660,
                                            "name": "self injury",
                                            "nsfwLevel": 32
                                        },
                                        {
                                            "id": 113976,
                                            "name": "extremist",
                                            "nsfwLevel": 32
                                        },
                                        {
                                            "id": 407770,
                                            "name": "hate speech",
                                            "nsfwLevel": 32
                                        },
                                        {
                                            "id": 198856,
                                            "name": "diapers",
                                            "nsfwLevel": 32
                                        },
                                        {
                                            "id": 114865,
                                            "name": "urine",
                                            "nsfwLevel": 32
                                        },
                                        {
                                            "id": 158125,
                                            "name": "menstruation",
                                            "nsfwLevel": 32
                                        },
                                        {
                                            "id": 117293,
                                            "name": "scat",
                                            "nsfwLevel": 32
                                        },
                                        {
                                            "id": 5218,
                                            "name": "hentai",
                                            "nsfwLevel": 8,
                                            "parentId": 111851
                                        },
                                        {
                                            "id": 243,
                                            "name": "porn",
                                            "nsfwLevel": 16,
                                            "parentId": 111991
                                        },
                                        {
                                            "id": 5218,
                                            "name": "hentai",
                                            "nsfwLevel": 16,
                                            "parentId": 111991
                                        },
                                        {
                                            "id": 243,
                                            "name": "porn",
                                            "nsfwLevel": 8,
                                            "parentId": 112683
                                        },
                                        {
                                            "id": 5218,
                                            "name": "hentai",
                                            "nsfwLevel": 8,
                                            "parentId": 112683
                                        },
                                        {
                                            "id": 243,
                                            "name": "porn",
                                            "nsfwLevel": 8,
                                            "parentId": 112481
                                        },
                                        {
                                            "id": 5218,
                                            "name": "hentai",
                                            "nsfwLevel": 8,
                                            "parentId": 112481
                                        },
                                        {
                                            "id": 1600,
                                            "name": "bukkake",
                                            "nsfwLevel": 16,
                                            "parentId": 111991
                                        },
                                        {
                                            "id": 3258,
                                            "name": "cumshot",
                                            "nsfwLevel": 16,
                                            "parentId": 111991
                                        },
                                        {
                                            "id": 5195,
                                            "name": "cum",
                                            "nsfwLevel": 16,
                                            "parentId": 111991
                                        },
                                        {
                                            "id": 6572,
                                            "name": "cumdrip",
                                            "nsfwLevel": 16,
                                            "parentId": 111991
                                        },
                                        {
                                            "id": 6573,
                                            "name": "cum in pussy",
                                            "nsfwLevel": 16,
                                            "parentId": 111991
                                        },
                                        {
                                            "id": 6626,
                                            "name": "cum on face",
                                            "nsfwLevel": 16,
                                            "parentId": 111991
                                        },
                                        {
                                            "id": 58491,
                                            "name": "cum on hair",
                                            "nsfwLevel": 16,
                                            "parentId": 111991
                                        },
                                        {
                                            "id": 58492,
                                            "name": "cum on body",
                                            "nsfwLevel": 16,
                                            "parentId": 111991
                                        },
                                        {
                                            "id": 58493,
                                            "name": "cum on tongue",
                                            "nsfwLevel": 16,
                                            "parentId": 111991
                                        },
                                        {
                                            "id": 78431,
                                            "name": "cum on hands",
                                            "nsfwLevel": 16,
                                            "parentId": 111991
                                        },
                                        {
                                            "id": 109814,
                                            "name": "cum in mouth",
                                            "nsfwLevel": 16,
                                            "parentId": 111991
                                        },
                                        {
                                            "id": 115043,
                                            "name": "cum on pussy",
                                            "nsfwLevel": 16,
                                            "parentId": 111991
                                        },
                                        {
                                            "id": 4818,
                                            "name": "eat_cum",
                                            "nsfwLevel": 16,
                                            "parentId": 111991
                                        },
                                        {
                                            "id": 2084,
                                            "name": "fellatio",
                                            "nsfwLevel": 16,
                                            "parentId": 111991
                                        },
                                        {
                                            "id": 3576,
                                            "name": "implied fellatio",
                                            "nsfwLevel": 16,
                                            "parentId": 111991
                                        },
                                        {
                                            "id": 58490,
                                            "name": "after fellatio",
                                            "nsfwLevel": 16,
                                            "parentId": 111991
                                        },
                                        {
                                            "id": 114629,
                                            "name": "triple fellatio",
                                            "nsfwLevel": 16,
                                            "parentId": 111991
                                        },
                                        {
                                            "id": 114824,
                                            "name": "autofellatio",
                                            "nsfwLevel": 16,
                                            "parentId": 111991
                                        },
                                        {
                                            "id": 115142,
                                            "name": "pov fellatio",
                                            "nsfwLevel": 16,
                                            "parentId": 111991
                                        },
                                        {
                                            "id": 115031,
                                            "name": "fucked silly",
                                            "nsfwLevel": 16,
                                            "parentId": 111991
                                        },
                                        {
                                            "id": 111592,
                                            "name": "presenting ass",
                                            "nsfwLevel": 4,
                                            "parentId": 112944
                                        },
                                        {
                                            "id": 111593,
                                            "name": "presenting pussy",
                                            "nsfwLevel": 4,
                                            "parentId": 112944
                                        },
                                        {
                                            "id": 111596,
                                            "name": "spreading legs",
                                            "nsfwLevel": 4,
                                            "parentId": 112944
                                        },
                                        {
                                            "id": 114420,
                                            "name": "spread legs",
                                            "nsfwLevel": 4,
                                            "parentId": 112944
                                        },
                                        {
                                            "id": 111943,
                                            "name": "swimwear",
                                            "nsfwLevel": 4,
                                            "parentId": 112070
                                        },
                                        {
                                            "id": 111943,
                                            "name": "swimwear",
                                            "nsfwLevel": 4,
                                            "parentId": 111969
                                        },
                                        {
                                            "id": 1718,
                                            "name": "lingerie",
                                            "nsfwLevel": 4,
                                            "parentId": 112070
                                        },
                                        {
                                            "id": 1718,
                                            "name": "lingerie",
                                            "nsfwLevel": 4,
                                            "parentId": 111969
                                        },
                                        {
                                            "id": 2392,
                                            "name": "bikini",
                                            "nsfwLevel": 4,
                                            "parentId": 112070
                                        },
                                        {
                                            "id": 111935,
                                            "name": "latex clothing",
                                            "nsfwLevel": 2,
                                            "parentId": 6924
                                        },
                                        {
                                            "id": 111935,
                                            "name": "latex clothing",
                                            "nsfwLevel": 4,
                                            "parentId": 112944
                                        }
                                    ],
                                    "blockedUsers": [],
                                    "blockedByUsers": []
                                },
                                "dataUpdateCount": 1,
                                "dataUpdatedAt": 1744862417148,
                                "error": null,
                                "errorUpdateCount": 0,
                                "errorUpdatedAt": 0,
                                "fetchFailureCount": 0,
                                "fetchFailureReason": null,
                                "fetchMeta": null,
                                "isInvalidated": false,
                                "status": "success",
                                "fetchStatus": "idle"
                            },
                            "queryKey": [
                                [
                                    "hiddenPreferences",
                                    "getHidden"
                                ],
                                {
                                    "type": "query"
                                }
                            ],
                            "queryHash": "[[\"hiddenPreferences\",\"getHidden\"],{\"type\":\"query\"}]"
                        },
                        {
                            "state": {
                                "data": [
                                    {
                                        "entityType": "ModelVersion",
                                        "entityId": 1643268,
                                        "hasAccess": false,
                                        "availability": "EarlyAccess",
                                        "permissions": 3
                                    }
                                ],
                                "dataUpdateCount": 1,
                                "dataUpdatedAt": 1744862417150,
                                "error": null,
                                "errorUpdateCount": 0,
                                "errorUpdatedAt": 0,
                                "fetchFailureCount": 0,
                                "fetchFailureReason": null,
                                "fetchMeta": null,
                                "isInvalidated": false,
                                "status": "success",
                                "fetchStatus": "idle"
                            },
                            "queryKey": [
                                [
                                    "common",
                                    "getEntityAccess"
                                ],
                                {
                                    "input": {
                                        "entityId": 1643268,
                                        "entityType": "ModelVersion"
                                    },
                                    "type": "query"
                                }
                            ],
                            "queryHash": "[[\"common\",\"getEntityAccess\"],{\"input\":{\"entityId\":1643268,\"entityType\":\"ModelVersion\"},\"type\":\"query\"}]"
                        },
                        {
                            "state": {
                                "data": {
                                    "id": 654541,
                                    "name": "Centaur Transformation [Illustrious | Pony XL]",
                                    "description": "<p>Lemme see those horse girls!</p><p></p><p>Prompt: <span style=\"color:#fab005\">centaur, horse legs, human torso, taur, animal ears</span></p><p></p><p>Strength: 0.7-1</p><p></p><p>If you can support me, that will also be greatly appreciated! I love making these fun LoRAs and I want to continue this.</p>",
                                    "poi": false,
                                    "minor": false,
                                    "nsfwLevel": 15,
                                    "nsfw": false,
                                    "type": "LORA",
                                    "uploadType": "Created",
                                    "updatedAt": "2025-04-10T02:49:47.286Z",
                                    "deletedAt": null,
                                    "deletedBy": null,
                                    "status": "Published",
                                    "checkpointType": null,
                                    "allowNoCredit": true,
                                    "allowCommercialUse": [
                                        "Image",
                                        "RentCivit",
                                        "Rent",
                                        "Sell"
                                    ],
                                    "allowDerivatives": true,
                                    "allowDifferentLicense": true,
                                    "licenses": [],
                                    "publishedAt": "2024-08-17T12:55:07.307Z",
                                    "locked": false,
                                    "meta": {
                                        "imageNsfw": "None",
                                        "imageNsfwLevel": 4
                                    },
                                    "earlyAccessDeadline": "2025-04-25T02:49:43.625Z",
                                    "mode": null,
                                    "availability": "Public",
                                    "lockedProperties": [],
                                    "reportStats": null,
                                    "user": {
                                        "id": 2782920,
                                        "image": "https://lh3.googleusercontent.com/a/ACg8ocI_4ntSQNDpBD0i4MGopLqjr2sylOLJ46VIgLjfcB7jYw=s96-c",
                                        "username": "GrimGr1m",
                                        "deletedAt": null,
                                        "rank": {
                                            "leaderboardRank": 166
                                        },
                                        "profilePicture": {
                                            "id": 20189182,
                                            "name": "profile pic.png",
                                            "url": "33cf60f6-a820-46d2-a3c3-5eb86037806f",
                                            "nsfwLevel": 8,
                                            "hash": "UcN]X_tlb]kX~oR.s=X9pwNyJ8V?xwWBMdo#",
                                            "userId": 2782920,
                                            "ingestion": "Scanned",
                                            "type": "image",
                                            "width": 1024,
                                            "height": 1824,
                                            "metadata": {
                                                "hash": "UcN]X_tlb]kX~oR.s=X9pwNyJ8V?xwWBMdo#",
                                                "size": 2312263,
                                                "width": 1024,
                                                "height": 1824,
                                                "userId": 2782920,
                                                "profilePicture": true
                                            }
                                        },
                                        "cosmetics": [
                                            {
                                                "data": null,
                                                "cosmetic": {
                                                    "id": 323,
                                                    "data": {
                                                        "url": "adc6421e-f379-418a-861c-38e29f0613a0"
                                                    },
                                                    "type": "Badge",
                                                    "source": "Purchase",
                                                    "name": "Tsundere Lover"
                                                }
                                            },
                                            {
                                                "data": null,
                                                "cosmetic": {
                                                    "id": 353,
                                                    "data": {
                                                        "url": "9188bca2-9843-4a7d-a56a-ffc4f5642675",
                                                        "offset": "30%"
                                                    },
                                                    "type": "ProfileDecoration",
                                                    "source": "Purchase",
                                                    "name": "240501 Animated Avatar 6"
                                                }
                                            },
                                            {
                                                "data": {
                                                    "donated": 2000,
                                                    "purchased": 0
                                                },
                                                "cosmetic": {
                                                    "id": 763,
                                                    "data": {
                                                        "glow": true,
                                                        "type": "holiday-lights",
                                                        "color": "red",
                                                        "texture": {
                                                            "url": "url('https://image.civitai.com/xG1nkqKTMzGDvpLrqFT7WA/aff9ee86-45f6-462a-a77d-06ec39483cc3/original=true/texture.png')",
                                                            "size": {
                                                                "width": 14,
                                                                "height": 14
                                                            }
                                                        },
                                                        "cssFrame": "linear-gradient(90deg, #34502B 4%, #7B9971 47%, #34502B 95%)",
                                                        "brightness": 0.75
                                                    },
                                                    "type": "ContentDecoration",
                                                    "source": "Event",
                                                    "name": "Holiday Garland 2024 - Red"
                                                }
                                            },
                                            {
                                                "data": null,
                                                "cosmetic": {
                                                    "id": 778,
                                                    "data": {
                                                        "glow": true,
                                                        "cssFrame": "linear-gradient(45deg, #fff7da 11%, #e8a560 28%, #f08828 46%, #7b3108 68%, #210d01 99%);"
                                                    },
                                                    "type": "ContentDecoration",
                                                    "source": "Purchase",
                                                    "name": "Toasted Marshmallow"
                                                }
                                            }
                                        ]
                                    },
                                    "modelVersions": [
                                        {
                                            "id": 1643268,
                                            "modelId": 654541,
                                            "name": "Illustrious",
                                            "description": null,
                                            "steps": null,
                                            "epochs": null,
                                            "clipSkip": null,
                                            "createdAt": "2025-04-10T02:44:09.458Z",
                                            "updatedAt": "2025-04-10T02:49:43.948Z",
                                            "trainedWords": [
                                                "centaur, horse legs, human torso, taur, animal ears"
                                            ],
                                            "trainingStatus": null,
                                            "trainingDetails": null,
                                            "inaccurate": false,
                                            "baseModel": "Illustrious",
                                            "baseModelType": null,
                                            "earlyAccessEndsAt": "2025-04-25T02:49:43.625Z",
                                            "earlyAccessConfig": {
                                                "timeframe": 15,
                                                "donationGoal": 10000,
                                                "downloadPrice": 200,
                                                "donationGoalId": 9064,
                                                "generationPrice": 50,
                                                "chargeForDownload": true,
                                                "chargeForGeneration": true,
                                                "donationGoalEnabled": true,
                                                "originalPublishedAt": "2025-04-10T02:49:43.625Z",
                                                "generationTrialLimit": 10
                                            },
                                            "status": "Published",
                                            "publishedAt": "2025-04-10T02:49:43.625Z",
                                            "meta": {
                                                "imageNsfwLevel": 4,
                                                "hadEarlyAccessPurchase": true
                                            },
                                            "vaeId": null,
                                            "settings": {},
                                            "requireAuth": true,
                                            "nsfwLevel": 15,
                                            "uploadType": "Created",
                                            "usageControl": "Download",
                                            "metrics": null,
                                            "files": [
                                                {
                                                    "id": 1543726,
                                                    "url": "https://civitai-delivery-worker-prod.5ac0637cfd0766c97916cefa3764fbdf.r2.cloudflarestorage.com/model/2782920/centaurTransformation.5Ear.safetensors",
                                                    "sizeKB": 223139.40234375,
                                                    "name": "Centaur_Transformation_Illustrious.safetensors",
                                                    "type": "Model",
                                                    "visibility": "Public",
                                                    "metadata": {
                                                        "fp": null,
                                                        "size": null,
                                                        "format": "SafeTensor"
                                                    },
                                                    "pickleScanResult": "Success",
                                                    "pickleScanMessage": "No Pickle imports",
                                                    "virusScanResult": "Success",
                                                    "virusScanMessage": null,
                                                    "scannedAt": "2025-04-10T02:51:33.407Z",
                                                    "modelVersionId": 1643268,
                                                    "hashes": [
                                                        {
                                                            "type": "AutoV1",
                                                            "hash": "458BD795"
                                                        },
                                                        {
                                                            "type": "AutoV2",
                                                            "hash": "524B90271C"
                                                        },
                                                        {
                                                            "type": "SHA256",
                                                            "hash": "524B90271C73B66D0231794C2E7A30A8FFCA7D6B2C8138CBDEE5682504D7DDE6"
                                                        },
                                                        {
                                                            "type": "CRC32",
                                                            "hash": "0D043A26"
                                                        },
                                                        {
                                                            "type": "BLAKE3",
                                                            "hash": "1A116836F655FEA756D6AAAD8FED8D874104DA64D996BB03BBDDA0A597E541D7"
                                                        },
                                                        {
                                                            "type": "AutoV3",
                                                            "hash": "29C69F0EF8C1"
                                                        }
                                                    ]
                                                }
                                            ],
                                            "generationCoverage": {
                                                "covered": true
                                            },
                                            "recommendedResources": [],
                                            "rank": {
                                                "generationCountAllTime": 46,
                                                "downloadCountAllTime": 10,
                                                "ratingCountAllTime": 0,
                                                "ratingAllTime": 0,
                                                "thumbsUpCountAllTime": 29,
                                                "thumbsDownCountAllTime": 0,
                                                "earnedAmountAllTime": 7
                                            },
                                            "posts": [
                                                {
                                                    "id": 15347492
                                                }
                                            ],
                                            "hashes": [
                                                "524b90271c73b66d0231794c2e7a30a8ffca7d6b2c8138cbdee5682504d7dde6"
                                            ],
                                            "earlyAccessDeadline": "2025-04-25T02:49:43.625Z",
                                            "canDownload": false,
                                            "canGenerate": true
                                        },
                                        {
                                            "id": 732302,
                                            "modelId": 654541,
                                            "name": "Pony",
                                            "description": null,
                                            "steps": null,
                                            "epochs": null,
                                            "clipSkip": null,
                                            "createdAt": "2024-08-17T06:45:13.780Z",
                                            "updatedAt": "2025-04-10T02:44:09.458Z",
                                            "trainedWords": [
                                                "centaur, horse legs, human torso, taur, animal ears"
                                            ],
                                            "trainingStatus": null,
                                            "trainingDetails": null,
                                            "inaccurate": false,
                                            "baseModel": "Pony",
                                            "baseModelType": null,
                                            "earlyAccessEndsAt": null,
                                            "earlyAccessConfig": null,
                                            "status": "Published",
                                            "publishedAt": "2024-08-17T12:55:07.307Z",
                                            "meta": {
                                                "imageNsfw": "None"
                                            },
                                            "vaeId": null,
                                            "settings": {},
                                            "requireAuth": true,
                                            "nsfwLevel": 7,
                                            "uploadType": "Created",
                                            "usageControl": "Download",
                                            "metrics": null,
                                            "files": [
                                                {
                                                    "id": 646424,
                                                    "url": "https://civitai-delivery-worker-prod.5ac0637cfd0766c97916cefa3764fbdf.r2.cloudflarestorage.com/model/2782920/centaurGirl.Xnnh.safetensors",
                                                    "sizeKB": 445805.32421875,
                                                    "name": "Centaur_Girl.safetensors",
                                                    "type": "Model",
                                                    "visibility": "Public",
                                                    "metadata": {
                                                        "fp": null,
                                                        "size": null,
                                                        "format": "SafeTensor"
                                                    },
                                                    "pickleScanResult": "Success",
                                                    "pickleScanMessage": "No Pickle imports",
                                                    "virusScanResult": "Success",
                                                    "virusScanMessage": null,
                                                    "scannedAt": "2024-08-17T06:56:17.941Z",
                                                    "modelVersionId": 732302,
                                                    "hashes": [
                                                        {
                                                            "type": "AutoV1",
                                                            "hash": "34C2A77F"
                                                        },
                                                        {
                                                            "type": "AutoV2",
                                                            "hash": "43A1C24B90"
                                                        },
                                                        {
                                                            "type": "SHA256",
                                                            "hash": "43A1C24B90B7ACDA9348D72BD24AA215B3C0107DE9CB68BB85244964648A9A19"
                                                        },
                                                        {
                                                            "type": "CRC32",
                                                            "hash": "0C7A9771"
                                                        },
                                                        {
                                                            "type": "BLAKE3",
                                                            "hash": "F9B423D0A605E46E1C5E334FA9B8307521C2BD251F4046665A8F7769467BF185"
                                                        },
                                                        {
                                                            "type": "AutoV3",
                                                            "hash": "B0FD36B4111F"
                                                        }
                                                    ]
                                                }
                                            ],
                                            "generationCoverage": {
                                                "covered": true
                                            },
                                            "recommendedResources": [],
                                            "rank": {
                                                "generationCountAllTime": 33433,
                                                "downloadCountAllTime": 1135,
                                                "ratingCountAllTime": 0,
                                                "ratingAllTime": 0,
                                                "thumbsUpCountAllTime": 202,
                                                "thumbsDownCountAllTime": 1,
                                                "earnedAmountAllTime": 10957
                                            },
                                            "posts": [
                                                {
                                                    "id": 5522375
                                                }
                                            ],
                                            "hashes": [
                                                "43a1c24b90b7acda9348d72bd24aa215b3c0107de9cb68bb85244964648a9a19"
                                            ],
                                            "earlyAccessDeadline": null,
                                            "canDownload": true,
                                            "canGenerate": true
                                        }
                                    ],
                                    "metrics": null,
                                    "rank": {
                                        "downloadCountAllTime": 1145,
                                        "favoriteCountAllTime": 0,
                                        "thumbsUpCountAllTime": 220,
                                        "thumbsDownCountAllTime": 1,
                                        "commentCountAllTime": 1,
                                        "ratingCountAllTime": 0,
                                        "ratingAllTime": 0,
                                        "tippedAmountCountAllTime": 1960,
                                        "imageCountAllTime": 0,
                                        "collectedCountAllTime": 101,
                                        "generationCountAllTime": 33479
                                    },
                                    "canGenerate": true,
                                    "hasSuggestedResources": false,
                                    "tagsOnModels": [
                                        {
                                            "tag": {
                                                "id": 4,
                                                "name": "anime",
                                                "isCategory": false
                                            }
                                        },
                                        {
                                            "tag": {
                                                "id": 190,
                                                "name": "sexy",
                                                "isCategory": false
                                            }
                                        },
                                        {
                                            "tag": {
                                                "id": 195,
                                                "name": "concept",
                                                "isCategory": true
                                            }
                                        },
                                        {
                                            "tag": {
                                                "id": 2703,
                                                "name": "centaur",
                                                "isCategory": false
                                            }
                                        },
                                        {
                                            "tag": {
                                                "id": 5133,
                                                "name": "woman",
                                                "isCategory": false
                                            }
                                        },
                                        {
                                            "tag": {
                                                "id": 5212,
                                                "name": "girls",
                                                "isCategory": false
                                            }
                                        },
                                        {
                                            "tag": {
                                                "id": 5269,
                                                "name": "video game",
                                                "isCategory": false
                                            }
                                        },
                                        {
                                            "tag": {
                                                "id": 111506,
                                                "name": "monster girl",
                                                "isCategory": false
                                            }
                                        },
                                        {
                                            "tag": {
                                                "id": 113937,
                                                "name": "lora",
                                                "isCategory": false
                                            }
                                        },
                                        {
                                            "tag": {
                                                "id": 137697,
                                                "name": "centaur girl",
                                                "isCategory": false
                                            }
                                        }
                                    ]
                                },
                                "dataUpdateCount": 1,
                                "dataUpdatedAt": 1744862417185,
                                "error": null,
                                "errorUpdateCount": 0,
                                "errorUpdatedAt": 0,
                                "fetchFailureCount": 0,
                                "fetchFailureReason": null,
                                "fetchMeta": null,
                                "isInvalidated": false,
                                "status": "success",
                                "fetchStatus": "idle"
                            },
                            "queryKey": [
                                [
                                    "model",
                                    "getById"
                                ],
                                {
                                    "input": {
                                        "id": 654541
                                    },
                                    "type": "query"
                                }
                            ],
                            "queryHash": "[[\"model\",\"getById\"],{\"input\":{\"id\":654541},\"type\":\"query\"}]"
                        },
                        {
                            "state": {
                                "data": null,
                                "dataUpdateCount": 1,
                                "dataUpdatedAt": 1744862417187,
                                "error": null,
                                "errorUpdateCount": 0,
                                "errorUpdatedAt": 0,
                                "fetchFailureCount": 0,
                                "fetchFailureReason": null,
                                "fetchMeta": null,
                                "isInvalidated": false,
                                "status": "success",
                                "fetchStatus": "idle"
                            },
                            "queryKey": [
                                [
                                    "model",
                                    "getCollectionShowcase"
                                ],
                                {
                                    "input": {
                                        "id": 654541
                                    },
                                    "type": "query"
                                }
                            ],
                            "queryHash": "[[\"model\",\"getCollectionShowcase\"],{\"input\":{\"id\":654541},\"type\":\"query\"}]"
                        }
                    ]
                },
                "meta": {
                    "values": {
                        "queries.2.state.data.updatedAt": [
                            "Date"
                        ],
                        "queries.2.state.data.publishedAt": [
                            "Date"
                        ],
                        "queries.2.state.data.earlyAccessDeadline": [
                            "Date"
                        ],
                        "queries.2.state.data.modelVersions.0.createdAt": [
                            "Date"
                        ],
                        "queries.2.state.data.modelVersions.0.updatedAt": [
                            "Date"
                        ],
                        "queries.2.state.data.modelVersions.0.earlyAccessEndsAt": [
                            "Date"
                        ],
                        "queries.2.state.data.modelVersions.0.publishedAt": [
                            "Date"
                        ],
                        "queries.2.state.data.modelVersions.0.metrics": [
                            "undefined"
                        ],
                        "queries.2.state.data.modelVersions.0.files.0.scannedAt": [
                            "Date"
                        ],
                        "queries.2.state.data.modelVersions.0.earlyAccessDeadline": [
                            "Date"
                        ],
                        "queries.2.state.data.modelVersions.1.createdAt": [
                            "Date"
                        ],
                        "queries.2.state.data.modelVersions.1.updatedAt": [
                            "Date"
                        ],
                        "queries.2.state.data.modelVersions.1.publishedAt": [
                            "Date"
                        ],
                        "queries.2.state.data.modelVersions.1.metrics": [
                            "undefined"
                        ],
                        "queries.2.state.data.modelVersions.1.files.0.scannedAt": [
                            "Date"
                        ],
                        "queries.2.state.data.metrics": [
                            "undefined"
                        ]
                    },
                    "referentialEqualities": {
                        "queries.2.state.data.modelVersions.0.earlyAccessEndsAt": [
                            "queries.2.state.data.modelVersions.0.earlyAccessDeadline"
                        ]
                    }
                }
            }
        },
        "__N_SSP": true
    },
    "page": "/models/[id]/[[...slug]]",
    "query": {
        "id": "654541"
    },
    "buildId": "qSuhsQvmA580E9k5a9wG5",
    "isFallback": false,
    "isExperimentalCompile": false,
    "gssp": true,
    "appGip": true,
    "locale": "en",
    "locales": [
        "en"
    ],
    "defaultLocale": "en",
    "scriptLoader": []
}